arolemgr/__init__.py
arolemgr/__main__.py
arolemgr/constants.py
arolemgr/context.py
arolemgr/release.py
arolemgr/_vendor/__init__.py
arolemgr/cli/__init__.py
arolemgr/cli/galaxy.py
arolemgr/cli/arguments/__init__.py
arolemgr/cli/arguments/option_helpers.py
arolemgr/cli/scripts/__init__.py
arolemgr/cli/scripts/ansible_connection_cli_stub.py
arolemgr/collections/__init__.py
arolemgr/collections/list.py
arolemgr/compat/__init__.py
arolemgr/compat/importlib_resources.py
arolemgr/compat/selectors.py
arolemgr/config/__init__.py
arolemgr/config/ansible_builtin_runtime.yml
arolemgr/config/base.yml
arolemgr/config/manager.py
arolemgr/errors/__init__.py
arolemgr/errors/yaml_strings.py
arolemgr/executor/__init__.py
arolemgr/executor/action_write_locks.py
arolemgr/executor/interpreter_discovery.py
arolemgr/executor/module_common.py
arolemgr/executor/play_iterator.py
arolemgr/executor/playbook_executor.py
arolemgr/executor/stats.py
arolemgr/executor/task_executor.py
arolemgr/executor/task_queue_manager.py
arolemgr/executor/task_result.py
arolemgr/executor/discovery/__init__.py
arolemgr/executor/discovery/python_target.py
arolemgr/executor/powershell/__init__.py
arolemgr/executor/powershell/module_manifest.py
arolemgr/executor/process/__init__.py
arolemgr/executor/process/worker.py
arolemgr/galaxy/__init__.py
arolemgr/galaxy/api.py
arolemgr/galaxy/role.py
arolemgr/galaxy/token.py
arolemgr/galaxy/user_agent.py
arolemgr/galaxy/collection/__init__.py
arolemgr/galaxy/collection/concrete_artifact_manager.py
arolemgr/galaxy/collection/galaxy_api_proxy.py
arolemgr/galaxy/collection/gpg.py
arolemgr/galaxy/data/collections_galaxy_meta.yml
arolemgr/galaxy/data/apb/Dockerfile.j2
arolemgr/galaxy/data/apb/Makefile.j2
arolemgr/galaxy/data/apb/README.md
arolemgr/galaxy/data/apb/apb.yml.j2
arolemgr/galaxy/data/apb/defaults/main.yml.j2
arolemgr/galaxy/data/apb/files/.git_keep
arolemgr/galaxy/data/apb/handlers/main.yml.j2
arolemgr/galaxy/data/apb/meta/main.yml.j2
arolemgr-0.2.0.dist-info/COPYING
arolemgr-0.2.0.dist-info/METADATA
arolemgr-0.2.0.dist-info/WHEEL
arolemgr-0.2.0.dist-info/entry_points.txt
arolemgr-0.2.0.dist-info/top_level.txt
arolemgr-0.2.0.dist-info/RECORD
