Metadata-Version: 2.1
Name: arolemgr
Version: 0.2.0
Summary: Advanced Role Manager
Home-page: https://github.com/michaelroosz/arolemgr
Author: Michael Roosz
Author-email: michael.roosz@web.de
License: GPLv3+
Project-URL: Bug Tracker, https://github.com/michaelroosz/arolemgr/issues
Project-URL: Source Code, https://github.com/michaelroosz/arolemgr
Classifier: Development Status :: 5 - Production/Stable
Classifier: Environment :: Console
Classifier: Intended Audience :: Developers
Classifier: Intended Audience :: Information Technology
Classifier: Intended Audience :: System Administrators
Classifier: License :: OSI Approved :: GNU General Public License v3 or later (GPLv3+)
Classifier: Natural Language :: English
Classifier: Operating System :: POSIX
Classifier: Programming Language :: Python :: 3
Classifier: Programming Language :: Python :: 3.10
Classifier: Programming Language :: Python :: 3.11
Classifier: Programming Language :: Python :: 3.12
Classifier: Programming Language :: Python :: 3 :: Only
Classifier: Topic :: System :: Installation/Setup
Classifier: Topic :: System :: Systems Administration
Classifier: Topic :: Utilities
Requires-Python: >=3.10
License-File: COPYING
Requires-Dist: jinja2 >=3.0.0
Requires-Dist: PyYAML >=5.1
Requires-Dist: cryptography
Requires-Dist: packaging
Requires-Dist: resolvelib <1.1.0,>=0.5.3
